apiflows.py
config.py
setup.py
utils.py
assertors/contains.py
assertors/eq.py
assertors/gt.py
assertors/gte.py
assertors/lt.py
assertors/lte.py
assertors/match.py
assertors/neq.py
models/apicase.py
apiflows-1.0.9.dist-info/METADATA
apiflows-1.0.9.dist-info/WHEEL
apiflows-1.0.9.dist-info/top_level.txt
apiflows-1.0.9.dist-info/RECORD
