Metadata-Version: 2.1
Name: apiflows
Version: 1.0.9
Summary: A yaml data-drive HTTP API testing tools.
Author-email: Allen <aiddroid@gmail.com>
Project-URL: Homepage, https://github.com/aiddroid/apiflows
Project-URL: Bug Tracker, https://github.com/aiddroid/apiflows
Classifier: Programming Language :: Python :: 3
Classifier: License :: OSI Approved :: MIT License
Classifier: Operating System :: OS Independent
Requires-Python: >=3.5
